README.rst
setup.py
dbmake/__init__.py
dbmake/commands.py
dbmake/common.py
dbmake/database.py
dbmake/db_tasks.py
dbmake/dbmake.py
dbmake/dbmake_cli.py
dbmake/doc_generator.py
dbmake/helper.py
dbmake/migrations.py
dbmake.egg-info/PKG-INFO
dbmake.egg-info/SOURCES.txt
dbmake.egg-info/dependency_links.txt
dbmake.egg-info/entry_points.txt
dbmake.egg-info/requires.txt
dbmake.egg-info/top_level.txt
test/__init__.py
test/test_helper.py