Metadata-Version: 1.1
Name: dbmake
Version: 0.1.3
Summary: DBAs friendly database schema migration tool
Home-page: https://github.com/splanger/dbmake
Author: Yuri Kroz
Author-email: splanger@gmail.com
License: License :: OSI Approved :: Apache Software License
Keywords: database db_management database_migration
Platform: UNKNOWN
Classifier: Development Status :: 4 - Beta
Classifier: Intended Audience :: Other Audience
Classifier: License :: OSI Approved :: Apache Software License
Classifier: Programming Language :: Python :: 2.7
